themepy/__init__.py
themepy/set_theme.py
themepy/theme.py
themepy/themes/__init__.py
themepy/themes/neon.txt
themepy/themes/sample-dark.txt
themepy/themes/sample-dark2.txt
themepy/themes/sample-light.txt
themepy/themes/sample-light2.txt
themepy-0.1.1.dist-info/LICENSE
themepy-0.1.1.dist-info/METADATA
themepy-0.1.1.dist-info/WHEEL
themepy-0.1.1.dist-info/top_level.txt
themepy-0.1.1.dist-info/RECORD
