Metadata-Version: 2.1
Name: themepy
Version: 0.1.1
Summary: a tools suite to manage themes in matplotlib
Home-page: https://github.com/petermckeeverPerform/themepy
Author: Peter McKeever
Author-email: hello@petermckeever.com
License: UNKNOWN
Platform: UNKNOWN
Classifier: Programming Language :: Python :: 3.7
Requires-Python: >=3.7
